README.md
setup.py
decoder/__init__.py
decoder/decoder.py
decoder.egg-info/PKG-INFO
decoder.egg-info/SOURCES.txt
decoder.egg-info/dependency_links.txt
decoder.egg-info/entry_points.txt
decoder.egg-info/not-zip-safe
decoder.egg-info/requires.txt
decoder.egg-info/top_level.txt