Metadata-Version: 2.1
Name: decoder
Version: 0.3
Summary: A simple script to try and decode a string in various encoding mechanisms regardless of it's (original) type.
Home-page: https://github.com/Anon-Exploiter/decoder
Author: Syed Umar Arfeen
Author-email: umar.arfeen@outlook.com
License: MIT
Platform: UNKNOWN
